hackedit_python/__init__.py
hackedit_python/add_import.py
hackedit_python/clean_pyc.py
hackedit_python/context_menus.py
hackedit_python/editor.py
hackedit_python/index.py
hackedit_python/interpreters.py
hackedit_python/open_module.py
hackedit_python/pyconsole.py
hackedit_python/pyqode_server.py
hackedit_python/refactor.py
hackedit_python/run.py
hackedit_python/system.py
hackedit_python/templates.py
hackedit_python/workspaces.py
hackedit_python/forms/__init__.py
hackedit_python/forms/dlg_create_virtualenv_ui.py
hackedit_python/forms/dlg_edit_breakpoints_ui.py
hackedit_python/forms/dlg_rope_rename_ui.py
hackedit_python/forms/hackedit_python_rc.py
hackedit_python/forms/settings_page_editor_ui.py
hackedit_python/forms/settings_page_interpreters_ui.py
hackedit_python/templates/python_library/.gitignore
hackedit_python/templates/python_library/README.rst
hackedit_python/templates/python_library/requirements.txt
hackedit_python/templates/python_library/setup.py
hackedit_python/templates/python_library/template.json
hackedit_python/templates/python_library/.hackedit/run.json
hackedit_python/templates/python_library/@package@/__init__.py
hackedit_python/templates/python_library/tests/test_@package@.py
hackedit_python/templates/python_script/@fn@.py
hackedit_python/templates/python_script/template.json
hackedit_python/vendor/__init__.py
hackedit_python/vendor/virtualenv.py
hackedit_python/vendor/rope/__init__.py
hackedit_python/vendor/rope/base/__init__.py
hackedit_python/vendor/rope/base/arguments.py
hackedit_python/vendor/rope/base/ast.py
hackedit_python/vendor/rope/base/astutils.py
hackedit_python/vendor/rope/base/builtins.py
hackedit_python/vendor/rope/base/change.py
hackedit_python/vendor/rope/base/codeanalyze.py
hackedit_python/vendor/rope/base/default_config.py
hackedit_python/vendor/rope/base/evaluate.py
hackedit_python/vendor/rope/base/exceptions.py
hackedit_python/vendor/rope/base/fscommands.py
hackedit_python-1.0a2.dist-info/DESCRIPTION.rst
hackedit_python-1.0a2.dist-info/METADATA
hackedit_python-1.0a2.dist-info/RECORD
hackedit_python-1.0a2.dist-info/WHEEL
hackedit_python-1.0a2.dist-info/entry_points.txt
hackedit_python-1.0a2.dist-info/metadata.json
hackedit_python-1.0a2.dist-info/top_level.txt
